lensegt/__init__.py
lensegt/lense/__init__.py
lensegt/lense/app.py
lensegt/my_backend/SQL_engine.py
lensegt/my_backend/__init__.py
lensegt/my_backend/cglense.py
lensegt/my_backend/chat_history.py
lensegt/my_backend/csv_engine.py
lensegt/my_backend/error_handling.py
lensegt/my_backend/loader.py
lensegt/my_backend/qna_engine.py
lensegt/my_backend/replace_file.py
lensegt/my_frontend/favicon.ico
lensegt/my_frontend/index.html
lensegt/my_frontend/assets/CGlenseFavicon-CIdCRnJ-.ico
lensegt/my_frontend/assets/Female-qqhXZmWu.svg
lensegt/my_frontend/assets/Male-BiYEbiTg.svg
lensegt/my_frontend/assets/Tourism-Bo7wcyxq.jpg
lensegt/my_frontend/assets/bg4-CfAbytIz.jpg
lensegt/my_frontend/assets/bh-Ciu3BGJR.jpg
lensegt/my_frontend/assets/energy-solutions-rgjFa6o4.png
lensegt/my_frontend/assets/finance-analytics-CrBYGfle.png
lensegt/my_frontend/assets/ianalyst-landingpage-CS7J4YPF.png
lensegt/my_frontend/assets/ibot-landingpage-CxHNAYyZ.png
lensegt/my_frontend/assets/index-Csz9sLvg.js
lensegt/my_frontend/assets/index-M-KZLfs2.css
lensegt/my_frontend/assets/infrastructure-D_pakpEV.png
lensegt/my_frontend/assets/legal-D--VpEKW.png
lensegt/my_frontend/assets/logo-white-MTSdTPk1.png
lensegt/my_frontend/assets/medical-D5hJbtlg.png
lensegt/my_frontend/assets/owl.video.play-BJo37keB.png
lensegt/my_frontend/assets/real-estate-BgUUNv75.png
lensegt/my_frontend/assets/retail-analytics-DMIVlxgB.png
lensegt/my_frontend/assets/white-logo-OMfBUHFP.png
lense-0.0.75.dist-info/LICENSE
lense-0.0.75.dist-info/METADATA
lense-0.0.75.dist-info/WHEEL
lense-0.0.75.dist-info/top_level.txt
lense-0.0.75.dist-info/RECORD
