Metadata-Version: 2.1
Name: lense
Version: 0.0.75
Summary: For QandA
Home-page: https://github.com/tandan-kumar-covalenseglobal/Lense
Author: Covalense
Author-email: Admin@covalenseglobal.com
Classifier: Programming Language :: Python :: 3
Classifier: License :: OSI Approved :: MIT License
Classifier: Operating System :: OS Independent
Requires-Python: >=3.11
License-File: LICENSE
Requires-Dist: required
Requires-Dist: pandas ==2.2.2
Requires-Dist: PyPDF2 ==3.0.1
Requires-Dist: python-docx ==1.1.0
Requires-Dist: python-pptx ==0.6.23
Requires-Dist: llama-index ==0.10.29
Requires-Dist: llama-index.llms.azure-openai ==0.1.5
Requires-Dist: llama-index.embeddings.azure-openai ==0.1.6
Requires-Dist: langchain ==0.1.16
Requires-Dist: huggingface-hub ==0.22.2
Requires-Dist: PyMuPDF ==1.24.1
Requires-Dist: sentence-transformers ==2.6.1
Requires-Dist: llama-index-embeddings-langchain ==0.1.2
Requires-Dist: llama-index-llms-langchain ==0.1.3
Requires-Dist: llama-index.experimental ==0.1.3
Requires-Dist: langchain-google-genai ==1.0.2
Requires-Dist: langchain-experimental ==0.0.57
Requires-Dist: langchain-openai ==0.1.3
Requires-Dist: psycopg2 ==2.9.9
Requires-Dist: fastapi ==0.110.2
Requires-Dist: python-multipart ==0.0.9
Requires-Dist: uvicorn ==0.29.0
Requires-Dist: langchain-community ==0.0.34
Requires-Dist: nest-asyncio
